sann.py
sann-1.0.4.dist-info/METADATA
sann-1.0.4.dist-info/WHEEL
sann-1.0.4.dist-info/licenses/LICENSE.md
sann-1.0.4.dist-info/RECORD
