Metadata-Version: 2.4
Name: sann
Version: 1.0.4
Summary: A Simple Artificial Neural Network (SANN) module, for educational use.
Project-URL: Homepage, https://ntoll.org/article/ai-curtain/
Project-URL: Documentation, https://sann.readthedocs.org/
Project-URL: Repository, https://github.com/ntoll/sann.git
Project-URL: Bug Tracker, https://github.com/ntoll/sann/issues
Project-URL: Changelog, https://github.com/ntoll/sann/blob/master/CHANGELOG.md
Author-email: "Nicholas H.Tollervey" <ntoll@ntoll.org>
Maintainer-email: "Nicholas H.Tollervey" <ntoll@ntoll.org>
License-Expression: MIT
License-File: LICENSE.md
Keywords: ai,ann,education,genetic algorithm,machine learning,neural network,neuro-evolution
Classifier: Development Status :: 4 - Beta
Classifier: Intended Audience :: Developers
Classifier: Intended Audience :: Education
Classifier: License :: OSI Approved :: MIT License
Classifier: Programming Language :: Python :: 3
Classifier: Programming Language :: Python :: Implementation :: MicroPython
Classifier: Topic :: Education
Classifier: Topic :: Scientific/Engineering :: Artificial Intelligence
Classifier: Topic :: Software Development :: Libraries :: Python Modules
Requires-Python: >=3.8
